zemfrog_resetdb/__init__.py
zemfrog_resetdb-1.0.1.dist-info/LICENSE
zemfrog_resetdb-1.0.1.dist-info/WHEEL
zemfrog_resetdb-1.0.1.dist-info/METADATA
zemfrog_resetdb-1.0.1.dist-info/RECORD
