Metadata-Version: 2.1
Name: zemfrog-resetdb
Version: 1.0.1
Summary: Command to reset the database for zemfrog
License: MIT
Author: aprilahijriyan
Author-email: hijriyan23@gmail.com
Requires-Python: >=3.6,<4.0
Classifier: License :: OSI Approved :: MIT License
Classifier: Programming Language :: Python :: 3
Classifier: Programming Language :: Python :: 3.6
Classifier: Programming Language :: Python :: 3.7
Classifier: Programming Language :: Python :: 3.8
Classifier: Programming Language :: Python :: 3.9
Requires-Dist: zemfrog (>=4.0.3,<5.0.0)
